src/main.py
password_enhance-0.0.1.dist-info/METADATA
password_enhance-0.0.1.dist-info/WHEEL
password_enhance-0.0.1.dist-info/top_level.txt
password_enhance-0.0.1.dist-info/RECORD
