Metadata-Version: 2.4
Name: password-enhance
Version: 0.0.1
Summary: Make a stronger password
Author-email: rifqanzalbina <zalbinarifqan19@gmail.com>
License: MIT
Project-URL: Homepage, https://github.com/rifqanzalbina/passwordstrengthd
Project-URL: Bug Tracker, https://github.com/rifqanzalbina/passwordstrength/issues
Classifier: Programming Language :: Python :: 3
Classifier: License :: OSI Approved :: MIT License
Classifier: Operating System :: OS Independent
Classifier: Natural Language :: Indonesian
Classifier: Topic :: Text Processing :: Linguistic
Requires-Python: >=3.6
